{
    "meta": {
        "portal_name": "laundry",
        "language": "en",
        "updated": "20150507"
    },
    "schema": {
        "html:portal": "http://en.recuweb.com/laundry/",
        "graph:videos": "http://en.recuweb.com/graph/v1.0/laundry/laundry/videos.json",
        "graph:news": "http://en.recuweb.com/graph/v1.0/laundry/laundry/news.json",
        "graph:blogs": "http://en.recuweb.com/graph/v1.0/laundry/laundry/blogs.json"
    },
    "items": {
        "dailymotion.com/2015/05/how-to-make-your-own-laundry-detergent": {
            "title": "How to: Make your own laundry detergent...",
            "snippet": "How to: Make your own laundry detergentAuthor: bluntgymTags: How to: Make your own laundry detergent Posted: 03 May 2015Rating:: 0...",
            "date": "2015-05-03",
            "author_name": "bluntgym",
            "categories": "laundry",
            "tags": "laundry",
            "recuweb_url": "http://en.recuweb.com/laundry/dailymotion.com/2015/05/how-to-make-your-own-laundry-detergent",
            "resource_url": "http://www.dailymotion.com/rss/relevance/lang/en/search/laundry/0?af=1",
            "source_url": "http://dailymotion.com/video/x2ovvs6_how-to-make-your-own-laundry-detergent_news",
            "img_url": "http://www.dailymotion.com/thumbnail/video/x2ovvs6_how-to-make-your-own-laundry-detergent_news"
        },
        "dailymotion.com/2015/04/student-s-robot-folds-laundry": {
            "title": "Student's Robot Folds Laundry...",
            "snippet": "Student's Robot Folds LaundryAuthor: VernitaLigonTags: Students Robot Folds Laundry Posted: 30 April 2015Rating:: 0...",
            "date": "2015-04-30",
            "author_name": "VernitaLigon",
            "categories": "laundry,students",
            "tags": "laundryauthor,laundry",
            "recuweb_url": "http://en.recuweb.com/students/dailymotion.com/2015/04/student-s-robot-folds-laundry",
            "resource_url": "http://www.dailymotion.com/rss/relevance/lang/en/search/laundry/0?af=1",
            "source_url": "http://dailymotion.com/video/x2okuaa_student-s-robot-folds-laundry_news",
            "img_url": "http://www.dailymotion.com/thumbnail/video/x2okuaa_student-s-robot-folds-laundry_news"
        },
        "dailymotion.com/2015/04/democratic-dirty-laundry": {
            "title": "Democratic Dirty Laundry...",
            "snippet": "Democratic Dirty LaundryAuthor: AnisaStarlingTags: Democratic Dirty Laundry Posted: 27 April 2015Rating:: 0...",
            "date": "2015-04-27",
            "author_name": "AnisaStarling",
            "categories": "laundry",
            "tags": "dirty,laundryauthor,laundry",
            "recuweb_url": "http://en.recuweb.com/laundry/dailymotion.com/2015/04/democratic-dirty-laundry",
            "resource_url": "http://www.dailymotion.com/rss/relevance/lang/en/search/laundry/0?af=1",
            "source_url": "http://dailymotion.com/video/x2o45p4_democratic-dirty-laundry_news",
            "img_url": "http://www.dailymotion.com/thumbnail/video/x2o45p4_democratic-dirty-laundry_news"
        },
        "dailymotion.com/2015/04/how-to-choose-laundry-equipment-new-jersey": {
            "title": "How To Choose Laundry Equipment New Jersey...",
            "snippet": "Visit for more infoAuthor: wwmarketing2Tags: business sales leadership marketing news Posted: 26 April 2015Rating:: 0...",
            "date": "2015-04-25",
            "author_name": "wwmarketing2",
            "categories": "business,leadership,marketing,laundry",
            "tags": "laundry,tags",
            "recuweb_url": "http://en.recuweb.com/laundry/dailymotion.com/2015/04/how-to-choose-laundry-equipment-new-jersey",
            "resource_url": "http://www.dailymotion.com/rss/relevance/lang/en/search/laundry/0?af=1",
            "source_url": "http://dailymotion.com/video/x2nzjis_how-to-choose-laundry-equipment-new-jersey_news",
            "img_url": "http://www.dailymotion.com/thumbnail/video/x2nzjis_how-to-choose-laundry-equipment-new-jersey_news"
        },
        "youtube.com/2015/04/cute-laundry-buddy": {
            "title": "CUTE LAUNDRY BUDDY!",
            "snippet": "CUTE LAUNDRY BUDDY! Get \"Who Knew\" on iTunes!! 14 Week Bumpdate! Be in my music video! See what we were doing 1... From: Daily Bumps Views: 135419 7860 ratings Time: 10:17 More in People & Blogs...",
            "date": "2015-04-19",
            "author_name": "Daily Bumps",
            "categories": "music,music-video,laundry",
            "tags": "doing,music,laundry",
            "recuweb_url": "http://en.recuweb.com/laundry/youtube.com/2015/04/cute-laundry-buddy",
            "resource_url": "http://gdata.youtube.com/feeds/base/videos?max-results=50&start-index=1&client=ytapi-youtube-search&v=2&q=laundry&hl=en&lang=en&lr=en&orderby=relevance_lang_en",
            "source_url": "http://youtube.com/watch?v=dDa91cqDatk&feature=youtube_gdata",
            "img_url": "http://img.youtube.com/vi/dDa91cqDatk/0.jpg"
        },
        "dailymotion.com/2015/04/laundry-hacks-to-make-your-life-easier": {
            "title": "Laundry Hacks To Make Your Life Easier...",
            "snippet": "So fresh and so clean, clean!Author: buzzfeedvideoTags: buzzfeed chores hacks house machine tips tricks washing laundry Posted: 18 April 2015Rating:: 0...",
            "date": "2015-04-18",
            "author_name": "buzzfeedvideo",
            "categories": "laundry,life",
            "tags": "laundry",
            "recuweb_url": "http://en.recuweb.com/life/dailymotion.com/2015/04/laundry-hacks-to-make-your-life-easier",
            "resource_url": "http://www.dailymotion.com/rss/relevance/lang/en/search/laundry/0?af=1",
            "source_url": "http://dailymotion.com/video/x2n47bd_laundry-hacks-to-make-your-life-easier_lifestyle",
            "img_url": "http://www.dailymotion.com/thumbnail/video/x2n47bd_laundry-hacks-to-make-your-life-easier_lifestyle"
        },
        "youtube.com/2015/04/one-guy-s-guide-to-doing-laundry": {
            "title": "One Guy's Guide To Doing Laundry...",
            "snippet": "One Guy's Guide To Doing Laundry All you need is soap, dirty clothes, a washer, dryer, and a good attitude. Check out more awesome BuzzFeedYellow videos! MUSIC Por Dinero, Healing Thoughts,... From: BuzzFeedYellow Views: 563069 21699 ratings Time:...",
            "date": "2015-04-03",
            "author_name": "BuzzFeedYellow",
            "categories": "music,laundry",
            "tags": "music,dirty,clothes,doing,laundry",
            "recuweb_url": "http://en.recuweb.com/laundry/youtube.com/2015/04/one-guy-s-guide-to-doing-laundry",
            "resource_url": "http://gdata.youtube.com/feeds/base/videos?max-results=50&start-index=1&client=ytapi-youtube-search&v=2&q=laundry&hl=en&lang=en&lr=en&orderby=relevance_lang_en",
            "source_url": "http://youtube.com/watch?v=2JsGJsdQuys&feature=youtube_gdata",
            "img_url": "http://img.youtube.com/vi/2JsGJsdQuys/0.jpg"
        },
        "youtube.com/2015/03/let-s-do-laundry": {
            "title": "Let's Do Laundry!",
            "snippet": "Let's Do Laundry! After the amazing response I received from my instructional video on how to make a latte, today I thought I would show you the easiest and most practical way to wash your clothes. Let's... From: LtMkilla Views: 200456 10815 ratings...",
            "date": "2015-03-31",
            "author_name": "LtMkilla",
            "categories": "laundry",
            "tags": "clothes,laundry",
            "recuweb_url": "http://en.recuweb.com/laundry/youtube.com/2015/03/let-s-do-laundry",
            "resource_url": "http://gdata.youtube.com/feeds/base/videos?max-results=50&start-index=1&client=ytapi-youtube-search&v=2&q=laundry&hl=en&lang=en&lr=en&orderby=relevance_lang_en",
            "source_url": "http://youtube.com/watch?v=H-PyAbMVO48&feature=youtube_gdata",
            "img_url": "http://img.youtube.com/vi/H-PyAbMVO48/0.jpg"
        },
        "dailymotion.com/2015/03/obama-s-laundry-list-of-treason-exposed": {
            "title": "Obama's Laundry List Of Treason Exposed...",
            "snippet": "Obama's Laundry List Of Treason ExposedAuthor: donganh360Tags: Obamas Laundry List Of Treason Posted: 06 March 2015Rating:: 0...",
            "date": "2015-03-06",
            "author_name": "donganh360",
            "categories": "laundry",
            "tags": "laundry,tags",
            "recuweb_url": "http://en.recuweb.com/laundry/dailymotion.com/2015/03/obama-s-laundry-list-of-treason-exposed",
            "resource_url": "http://www.dailymotion.com/rss/relevance/lang/en/search/laundry/0?af=1",
            "source_url": "http://dailymotion.com/video/x2isy8o_obama-s-laundry-list-of-treason-exposed_news",
            "img_url": "http://www.dailymotion.com/thumbnail/video/x2isy8o_obama-s-laundry-list-of-treason-exposed_news"
        },
        "youtube.com/2015/02/you-wont-believe-what-this-mother-of-6-did-to-totally": {
            "title": "You Wont Believe What This Mother of 6 Did to Totally Rock Her Laundry Space...",
            "snippet": "You Wont Believe What This Mother of 6 Did to Totally Rock Her Laundry Space See the 8 clever DIY solutions this busy mom came up with to take her laundry room from... From: HouzzTV Views: 4171499 2321 ratings Time: 03:31 More in Howto & Style...",
            "date": "2015-02-27",
            "author_name": "HouzzTV",
            "categories": "laundry",
            "tags": "laundry",
            "recuweb_url": "http://en.recuweb.com/laundry/youtube.com/2015/02/you-wont-believe-what-this-mother-of-6-did-to-totally",
            "resource_url": "http://gdata.youtube.com/feeds/base/videos?max-results=50&start-index=1&client=ytapi-youtube-search&v=2&q=laundry&hl=en&lang=en&lr=en&orderby=relevance_lang_en",
            "source_url": "http://youtube.com/watch?v=eVfTP4UnnmU&feature=youtube_gdata",
            "img_url": "http://img.youtube.com/vi/eVfTP4UnnmU/0.jpg"
        }
    }
}