{
    "meta": {
        "portal_name": "memory",
        "language": "en",
        "updated": "20150503"
    },
    "schema": {
        "html:portal": "http://en.recuweb.com/memory/",
        "graph:videos": "http://en.recuweb.com/graph/v1.0/memory/memory/videos.json",
        "graph:news": "http://en.recuweb.com/graph/v1.0/memory/memory/news.json",
        "graph:blogs": "http://en.recuweb.com/graph/v1.0/memory/memory/blogs.json"
    },
    "items": {
        "dailymotion.com/2015/05/memory-loss-amazing-tips-on-how-to-treat": {
            "title": "MEMORY LOSS! AMAZING TIPS ON HOW TO TREAT MEMORY LOSS!",
            "snippet": "MEMORY LOSS! AMAZING TIPS ON HOW TO TREAT MEMORY LOSS!Author: GoldenDudleyTags: MEMORY LOSS AMAZING TIPS ON HOW TO TREAT Posted: 02 May 2015Rating:: 0...",
            "date": "2015-05-02",
            "author_name": "GoldenDudley",
            "categories": "memory",
            "tags": "tips,memory",
            "recuweb_url": "http://en.recuweb.com/memory/dailymotion.com/2015/05/memory-loss-amazing-tips-on-how-to-treat",
            "resource_url": "http://www.dailymotion.com/rss/relevance/lang/en/search/memory+memory/0?af=1",
            "source_url": "http://dailymotion.com/video/x2otp76_memory-loss-amazing-tips-on-how-to-treat-memory-loss_tech",
            "img_url": "http://www.dailymotion.com/thumbnail/video/x2otp76_memory-loss-amazing-tips-on-how-to-treat-memory-loss_tech"
        },
        "dailymotion.com/2015/04/ripjaws-x-memory-16gb-1600mhz-240": {
            "title": "Ripjaws-X Memory Memory 16GB (1600MHz, 240...",
            "snippet": "Ripjaws-X Memory Memory 16GB (1600MHz, 240 Feature Upgrade Type:Generic Capacity:16 GB: 2 x 8 GB Compatible Slots:2 x memory - DIMM 240-pin, Technology:DDR3 SDRAM, Features:Heat sink, dual channel, unbuffered, Type:DRAM, Form Factor:DIMM 240-pin,...",
            "date": "2015-04-27",
            "author_name": "Prad1970",
            "categories": "memory,technology",
            "tags": "memory",
            "recuweb_url": "http://en.recuweb.com/technology/dailymotion.com/2015/04/ripjaws-x-memory-16gb-1600mhz-240",
            "resource_url": "http://www.dailymotion.com/rss/relevance/lang/en/search/memory+memory/0?af=1",
            "source_url": "http://dailymotion.com/video/x2o6yd3_g-skill-ripjaws-x-memory-memory-16gb-1600mhz-240_tech",
            "img_url": "http://www.dailymotion.com/thumbnail/video/x2o6yd3_g-skill-ripjaws-x-memory-memory-16gb-1600mhz-240_tech"
        },
        "youtube.com/2015/04/urf-in-loving-memory-2": {
            "title": "URF In Loving Memory 2...",
            "snippet": "URF In Loving Memory 2 Hey guys, VULCUN really makes LCS games a lot more fun, try it for free and you will see -- Buy gaming clothes at From: DanteAxeProduction Views: 360729 13088 ratings Time: 02:25 More in Film & Animation...",
            "date": "2015-04-24",
            "author_name": "DanteAxeProduction",
            "categories": "memory",
            "tags": "memory",
            "recuweb_url": "http://en.recuweb.com/memory/youtube.com/2015/04/urf-in-loving-memory-2",
            "resource_url": "http://gdata.youtube.com/feeds/base/videos?max-results=50&start-index=1&client=ytapi-youtube-search&v=2&q=memory%2Bmemory&hl=en&lang=en&lr=en&orderby=relevance_lang_en",
            "source_url": "http://youtube.com/watch?v=Ky2-qm4xY7o&feature=youtube_gdata",
            "img_url": "http://img.youtube.com/vi/Ky2-qm4xY7o/0.jpg"
        },
        "dailymotion.com/2015/04/photographic-memory-training-learning-tips": {
            "title": "photographic memory training - photographic memory learning tips...",
            "snippet": "photographic memory training - photographic memory learning tipsAuthor: BurnieMakhiTags: photographic memory training - learning tips Posted: 24 April 2015Rating:: 0...",
            "date": "2015-04-24",
            "author_name": "BurnieMakhi",
            "categories": "learning,memory",
            "tags": "tips,photographic,photographic-memory,memory,training",
            "recuweb_url": "http://en.recuweb.com/memory/dailymotion.com/2015/04/photographic-memory-training-learning-tips",
            "resource_url": "http://www.dailymotion.com/rss/relevance/lang/en/search/memory+memory/0?af=1",
            "source_url": "http://dailymotion.com/video/x2nrm4x_photographic-memory-training-photographic-memory-learning-tips_lifestyle",
            "img_url": "http://www.dailymotion.com/thumbnail/video/x2nrm4x_photographic-memory-training-photographic-memory-learning-tips_lifestyle"
        },
        "youtube.com/2015/04/zedd-addicted-to-a-memory-audio-ft-bahari": {
            "title": "Zedd - Addicted To A Memory (Audio) ft. Bahari...",
            "snippet": "Zedd - Addicted To A Memory (Audio) ft. Bahari \"True Colors\" album 5/19/2015 Pre-order now on iTunes and get \"Addicted To A Memory instantly: From: ZEDDVEVO Views: 1499127 42131 ratings Time: 05:02 More in Music...",
            "date": "2015-04-14",
            "author_name": "ZEDDVEVO",
            "categories": "memory,music",
            "tags": "memory,album,order,music",
            "recuweb_url": "http://en.recuweb.com/music/youtube.com/2015/04/zedd-addicted-to-a-memory-audio-ft-bahari",
            "resource_url": "http://gdata.youtube.com/feeds/base/videos?max-results=50&start-index=1&client=ytapi-youtube-search&v=2&q=memory%2Bmemory&hl=en&lang=en&lr=en&orderby=relevance_lang_en",
            "source_url": "http://youtube.com/watch?v=ZqJiXLJs_Pg&feature=youtube_gdata",
            "img_url": "http://img.youtube.com/vi/ZqJiXLJs_Pg/0.jpg"
        },
        "dailymotion.com/2015/04/how-are-memories-processed-memory-basics": {
            "title": "How are memories processed?: Memory Basics...",
            "snippet": "How are memories processed?: Arthur Bornstein (Founder, The Bornstein School for Memory Training)Author: tohealthTags: neuropsychological assessment consciousness Posted: 13 April 2015Rating:: 0...",
            "date": "2015-04-13",
            "author_name": "tohealth",
            "categories": "consciousness,memory,school",
            "tags": "neuropsychological,neuropsychological-assessment,neuropsychological-assessment-consciousness,assessment,assessment-consciousness,consciousness,memory,memory_training,training,bornstein,bornstein_school,school,arthur,arthur_bornstein,memory_basics,basics,founder,tohealthtags",
            "recuweb_url": "http://en.recuweb.com/school/dailymotion.com/2015/04/how-are-memories-processed-memory-basics",
            "resource_url": "http://www.dailymotion.com/rss/relevance/lang/en/search/memory+memory/0?af=1",
            "source_url": "http://dailymotion.com/video/x2maycx_how-are-memories-processed-memory-basics_lifestyle",
            "img_url": "http://www.dailymotion.com/thumbnail/video/x2maycx_how-are-memories-processed-memory-basics_lifestyle"
        },
        "dailymotion.com/2015/04/what-is-photographic-memory-basics": {
            "title": "What is photographic memory?: Memory Basics...",
            "snippet": "What is \"photographic memory\"?: Arthur Bornstein (Founder, The Bornstein School for Memory Training)Author: tohealthTags: neuropsychological assessment consciousness Posted: 13 April 2015Rating:: 0...",
            "date": "2015-04-13",
            "author_name": "tohealth",
            "categories": "consciousness,memory,school",
            "tags": "neuropsychological,neuropsychological-assessment,neuropsychological-assessment-consciousness,assessment,assessment-consciousness,consciousness,memory,memory_training,training,bornstein,bornstein_school,school,arthur,arthur_bornstein,photographic,photographic-memory,memory_basics,basics,founder,tohealthtags",
            "recuweb_url": "http://en.recuweb.com/school/dailymotion.com/2015/04/what-is-photographic-memory-basics",
            "resource_url": "http://www.dailymotion.com/rss/relevance/lang/en/search/memory+memory/0?af=1",
            "source_url": "http://dailymotion.com/video/x2mayd2_what-is-photographic-memory-memory-basics_lifestyle",
            "img_url": "http://www.dailymotion.com/thumbnail/video/x2mayd2_what-is-photographic-memory-memory-basics_lifestyle"
        },
        "dailymotion.com/2015/04/what-is-short-term-memory-basics": {
            "title": "What is short-term memory?: Memory Basics...",
            "snippet": "What is \"short-term memory\"?: Arthur Bornstein (Founder, The Bornstein School for Memory Training)Author: tohealthTags: neuropsychological assessment consciousness Posted: 13 April 2015Rating:: 0...",
            "date": "2015-04-13",
            "author_name": "tohealth",
            "categories": "consciousness,memory,school",
            "tags": "neuropsychological,neuropsychological-assessment,neuropsychological-assessment-consciousness,assessment,assessment-consciousness,consciousness,memory,memory_training,training,bornstein,bornstein_school,school,arthur,arthur_bornstein,memory_basics,basics,founder,tohealthtags",
            "recuweb_url": "http://en.recuweb.com/school/dailymotion.com/2015/04/what-is-short-term-memory-basics",
            "resource_url": "http://www.dailymotion.com/rss/relevance/lang/en/search/memory+memory/0?af=1",
            "source_url": "http://dailymotion.com/video/x2may8c_what-is-short-term-memory-memory-basics_lifestyle",
            "img_url": "http://www.dailymotion.com/thumbnail/video/x2may8c_what-is-short-term-memory-memory-basics_lifestyle"
        },
        "dailymotion.com/2015/04/what-is-memory-basics": {
            "title": "What is memory?: Memory Basics...",
            "snippet": "What is memory?: Arthur Bornstein (Founder, The Bornstein School for Memory Training)Author: tohealthTags: neuropsychological assessment consciousness Posted: 13 April 2015Rating:: 0...",
            "date": "2015-04-13",
            "author_name": "tohealth",
            "categories": "consciousness,memory,school",
            "tags": "neuropsychological,neuropsychological-assessment,neuropsychological-assessment-consciousness,assessment,assessment-consciousness,consciousness,memory,memory_training,training,bornstein,bornstein_school,school,arthur,arthur_bornstein,memory_basics,basics,founder,tohealthtags",
            "recuweb_url": "http://en.recuweb.com/school/dailymotion.com/2015/04/what-is-memory-basics",
            "resource_url": "http://www.dailymotion.com/rss/relevance/lang/en/search/memory+memory/0?af=1",
            "source_url": "http://dailymotion.com/video/x2may4v_what-is-memory-memory-basics_lifestyle",
            "img_url": "http://www.dailymotion.com/thumbnail/video/x2may4v_what-is-memory-memory-basics_lifestyle"
        },
        "youtube.com/2015/04/between-the-buried-and-me-memory-palace-official": {
            "title": "Between the Buried and Me Memory Palace (OFFICIAL)...",
            "snippet": "Between the Buried and Me \"Memory Palace\" (OFFICIAL) Order Here: Between the Buried and Me \"Memory Palace\" from the album \"Coma Ecliptic\". From: Metal Blade Records Views: 160906 3329 ratings Time: 09:57 More in Music...",
            "date": "2015-04-03",
            "author_name": "Metal Blade Records",
            "categories": "coma,memory,music",
            "tags": "album,order,memory,music",
            "recuweb_url": "http://en.recuweb.com/music/youtube.com/2015/04/between-the-buried-and-me-memory-palace-official",
            "resource_url": "http://gdata.youtube.com/feeds/base/videos?max-results=50&start-index=1&client=ytapi-youtube-search&v=2&q=memory%2Bmemory&hl=en&lang=en&lr=en&orderby=relevance_lang_en",
            "source_url": "http://youtube.com/watch?v=CEpu2keRMwI&feature=youtube_gdata",
            "img_url": "http://img.youtube.com/vi/CEpu2keRMwI/0.jpg"
        }
    }
}