{
    "meta": {
        "portal_name": "birdwatching",
        "language": "en",
        "updated": "20150502"
    },
    "schema": {
        "html:portal": "http://en.recuweb.com/birdwatching/",
        "graph:videos": "http://en.recuweb.com/graph/v1.0/birdwatching/birdwatching/videos.json",
        "graph:news": "http://en.recuweb.com/graph/v1.0/birdwatching/birdwatching/news.json",
        "graph:blogs": "http://en.recuweb.com/graph/v1.0/birdwatching/birdwatching/blogs.json"
    },
    "items": {
        "dailymotion.com/2015/04/wild-birdwatching-hd": {
            "title": "Wild birdwatching HD...",
            "snippet": "Wild birdwatching [HD]Author: AlbertHinkleTags: Wild birdwatching HD Posted: 23 April 2015Rating:: 0...",
            "date": "2015-04-23",
            "author_name": "AlbertHinkle",
            "tags": "bird,ing",
            "recuweb_url": "http://en.recuweb.com/dailymotion.com/2015/04/wild-birdwatching-hd",
            "resource_url": "http://www.dailymotion.com/rss/relevance/lang/en/search/birdwatching+birdwatching/0?af=1",
            "source_url": "http://dailymotion.com/video/x2nnhow_wild-birdwatching-hd_animals",
            "img_url": "http://www.dailymotion.com/thumbnail/video/x2nnhow_wild-birdwatching-hd_animals"
        },
        "dailymotion.com/2015/04/birdwatching-thailand-chiang-mai": {
            "title": "Birdwatching Thailand - Chiang Mai...",
            "snippet": "Birdwatching Thailand - Chiang MaiAuthor: ColtonLymanTags: Birdwatching Thailand - Chiang Mai Posted: 22 April 2015Rating:: 0...",
            "date": "2015-04-22",
            "author_name": "ColtonLyman",
            "tags": "bird,ing",
            "recuweb_url": "http://en.recuweb.com/dailymotion.com/2015/04/birdwatching-thailand-chiang-mai",
            "resource_url": "http://www.dailymotion.com/rss/relevance/lang/en/search/birdwatching+birdwatching/0?af=1",
            "source_url": "http://dailymotion.com/video/x2niz9g_birdwatching-thailand-chiang-mai_animals",
            "img_url": "http://www.dailymotion.com/thumbnail/video/x2niz9g_birdwatching-thailand-chiang-mai_animals"
        },
        "youtube.com/2015/04/sylas-brown-bird-watching": {
            "title": "Sylas Brown: Bird-watching...",
            "snippet": "Sylas Brown: Bird-watching It's not a hobby... it's a lifestyle. Part 1 - Part 2 - Part 3... From: InfraBren Views: 13436 1500 ratings Time: 03:25 More in Entertainment...",
            "date": "2015-04-15",
            "author_name": "InfraBren",
            "categories": "entertainment",
            "tags": "bird,ing",
            "recuweb_url": "http://en.recuweb.com/entertainment/youtube.com/2015/04/sylas-brown-bird-watching",
            "resource_url": "http://gdata.youtube.com/feeds/base/videos?max-results=50&start-index=1&client=ytapi-youtube-search&v=2&q=birdwatching%2Bbirdwatching&hl=en&lang=en&lr=en&orderby=relevance_lang_en",
            "source_url": "http://youtube.com/watch?v=TD1dWQOh5eY&feature=youtube_gdata",
            "img_url": "http://img.youtube.com/vi/TD1dWQOh5eY/0.jpg"
        },
        "dailymotion.com/2015/04/birdwatching-at-rspb-titchwell-marsh": {
            "title": "Birdwatching at RSPB Titchwell Marsh...",
            "snippet": "Birdwatching at RSPB Titchwell MarshAuthor: thighmoroseTags: Birdwatching at RSPB Titchwell Marsh Posted: 05 April 2015Rating:: 0...",
            "date": "2015-04-05",
            "author_name": "thighmorose",
            "tags": "rspb,ing,bird",
            "recuweb_url": "http://en.recuweb.com/dailymotion.com/2015/04/birdwatching-at-rspb-titchwell-marsh",
            "resource_url": "http://www.dailymotion.com/rss/relevance/lang/en/search/birdwatching+birdwatching/0?af=1",
            "source_url": "http://dailymotion.com/video/x2ls2sy_birdwatching-at-rspb-titchwell-marsh_animals",
            "img_url": "http://www.dailymotion.com/thumbnail/video/x2ls2sy_birdwatching-at-rspb-titchwell-marsh_animals"
        },
        "dailymotion.com/2015/04/download-rspb-pocket-garden-birdwatch-ebook-pdf-epub": {
            "title": "Download RSPB Pocket Garden Birdwatch ebook PDF EPUB...",
            "snippet": "Download RSPB Pocket Garden Birdwatch by Mark Ward - mirror 1 --- mirror 2 --- mirror 3 -- --------------- Synopsis: Get out into the garden and get birdspotting with the RSPBBirdwatching can be done from your doorstep with RSPB Pocket Garden...",
            "date": "2015-04-04",
            "author_name": "inenbumur1976",
            "categories": "ebook",
            "tags": "rspb,ing,bird,ebook",
            "recuweb_url": "http://en.recuweb.com/ebook/dailymotion.com/2015/04/download-rspb-pocket-garden-birdwatch-ebook-pdf-epub",
            "resource_url": "http://www.dailymotion.com/rss/relevance/lang/en/search/birdwatching+birdwatching/0?af=1",
            "source_url": "http://dailymotion.com/video/x2lqkxn_download-rspb-pocket-garden-birdwatch-ebook-pdf-epub_videogames",
            "img_url": "http://www.dailymotion.com/thumbnail/video/x2lqkxn_download-rspb-pocket-garden-birdwatch-ebook-pdf-epub_videogames"
        },
        "youtube.com/2015/03/conan-travels-birdwatching-in-central-park-5-12-05": {
            "title": "Conan Travels - Birdwatching in Central Park - 5/12/05...",
            "snippet": "Conan Travels - \"Birdwatching in Central Park\" - 5/12/05 Conan Travels - \"Birdwatching in Central Park\" - 5/12/05. From: Inflatable Conans Views: 16038 122 ratings Time: 08:31 More in Comedy...",
            "date": "2015-03-21",
            "author_name": "Inflatable Conans",
            "categories": "travel,comedy",
            "tags": "ing,bird",
            "recuweb_url": "http://en.recuweb.com/comedy/youtube.com/2015/03/conan-travels-birdwatching-in-central-park-5-12-05",
            "resource_url": "http://gdata.youtube.com/feeds/base/videos?max-results=50&start-index=1&client=ytapi-youtube-search&v=2&q=birdwatching%2Bbirdwatching&hl=en&lang=en&lr=en&orderby=relevance_lang_en",
            "source_url": "http://youtube.com/watch?v=xRLyXuAFVJs&feature=youtube_gdata",
            "img_url": "http://img.youtube.com/vi/xRLyXuAFVJs/0.jpg"
        },
        "youtube.com/2014/11/birdwatching-california-50-species": {
            "title": "Birdwatching California 50 species...",
            "snippet": "Birdwatching California 50 species An overview of birds that can frequently be spotted in the gardens, parks, beaches of San Francisco and the surrounding areas. Recorded with a Panasonic HC-X900 camcorder and a Sony... From: Guy Marchal Views: 97 1...",
            "date": "2014-11-12",
            "author_name": "Guy Marchal",
            "tags": "bird,ing,california",
            "recuweb_url": "http://en.recuweb.com/youtube.com/2014/11/birdwatching-california-50-species",
            "resource_url": "http://gdata.youtube.com/feeds/base/videos?max-results=50&start-index=1&client=ytapi-youtube-search&v=2&q=birdwatching&hl=en&lang=en&lr=en&orderby=relevance_lang_en",
            "source_url": "http://youtube.com/watch?v=KHw0KTw8j_g&feature=youtube_gdata",
            "img_url": "http://img.youtube.com/vi/KHw0KTw8j_g/0.jpg"
        },
        "dailymotion.com/2014/08/download-read-ebook-a-history-of-birdwatching-in-100-objects-free": {
            "title": "Download/Read (eBook) A History of Birdwatching in 100 Objects free 9DdX...",
            "snippet": "Read online or Download A History of Birdwatching in 100 Objects by David Callahan and Dominic Mitchell This book looks at 100 items that have profoundly shaped how people watched, studied and engaged with the avian world. Each item contains around...",
            "date": "2014-08-24",
            "author_name": "fuxewapuze",
            "categories": "ebook",
            "tags": "ing,ebook,bird",
            "recuweb_url": "http://en.recuweb.com/ebook/dailymotion.com/2014/08/download-read-ebook-a-history-of-birdwatching-in-100-objects-free",
            "resource_url": "http://www.dailymotion.com/rss/relevance/lang/en/search/birdwatching+birdwatching/0?af=1",
            "source_url": "http://dailymotion.com/video/x24fw4a_download-read-ebook-a-history-of-birdwatching-in-100-objects-free-9ddx_tech",
            "img_url": "http://www.dailymotion.com/thumbnail/video/x24fw4a_download-read-ebook-a-history-of-birdwatching-in-100-objects-free-9ddx_tech"
        },
        "youtube.com/2014/05/backyard-bird-watching-house-finch-nest-5-weeks-complete-documentary": {
            "title": "Backyard Bird Watching: House Finch Nest 5 Weeks Complete Documentary...",
            "snippet": "Backyard Bird Watching: House Finch Nest 5 Weeks Complete Documentary Filmed over the course of 5 weeks, from Eggs to Baby Flying away, shot in Pasadena California. From: toorima X Views: 67618 216 ratings Time: 32:39 More in Pets & Animals...",
            "date": "2014-05-05",
            "author_name": "toorima X",
            "categories": "pets,animals",
            "tags": "california,bird,ing",
            "recuweb_url": "http://en.recuweb.com/animals/youtube.com/2014/05/backyard-bird-watching-house-finch-nest-5-weeks-complete-documentary",
            "resource_url": "http://gdata.youtube.com/feeds/base/videos?max-results=50&start-index=1&client=ytapi-youtube-search&v=2&q=birdwatching%2Bbirdwatching&hl=en&lang=en&lr=en&orderby=relevance_lang_en",
            "source_url": "http://youtube.com/watch?v=yB7zkxJ5EyA&feature=youtube_gdata",
            "img_url": "http://img.youtube.com/vi/yB7zkxJ5EyA/0.jpg"
        },
        "youtube.com/2014/04/naturist-bird-watching-miss-hybrid": {
            "title": "Naturist Bird Watching: Miss Hybrid...",
            "snippet": "Naturist Bird Watching: Miss Hybrid On the beach with only thin white fabric hiding my nipples to keep this video youtube friendly. Wait until you see the size of the bird I am feeding! From: MissHybridXXX Views: 306931 309 ratings Time: 16:47 More...",
            "date": "2014-04-20",
            "author_name": "MissHybridXXX",
            "tags": "bird,ing",
            "recuweb_url": "http://en.recuweb.com/youtube.com/2014/04/naturist-bird-watching-miss-hybrid",
            "resource_url": "http://gdata.youtube.com/feeds/base/videos?max-results=50&start-index=1&client=ytapi-youtube-search&v=2&q=birdwatching%2Bbirdwatching&hl=en&lang=en&lr=en&orderby=relevance_lang_en",
            "source_url": "http://youtube.com/watch?v=GFmnDSMleR8&feature=youtube_gdata",
            "img_url": "http://img.youtube.com/vi/GFmnDSMleR8/0.jpg"
        }
    }
}